randomity/__init__.py
randomity/_utils/__init__.py
randomity/_utils/check_param.py
randomity/_utils/check_prime.py
randomity/_utils/compute_score.py
randomity/_utils/draw_histogram.py
randomity/_utils/gen_seed.py
randomity/_utils/gen_test_vector.py
randomity/_utils/normalization_config.py
randomity/_utils/_tests/__init__.py
randomity/_utils/_tests/chisqr_tst.py
randomity/_utils/_tests/entropy_tst.py
randomity/_utils/_tests/eqdist_tst.py
randomity/_utils/_tests/freq_tst.py
randomity/_utils/_tests/ftt_tst.py
randomity/_utils/_tests/gap_tst.py
randomity/_utils/_tests/ks_tst.py
randomity/_utils/_tests/permute_tst.py
randomity/_utils/_tests/serial_tst.py
randomity/evaluate/__init__.py
randomity/evaluate/inspectRandom.py
randomity/evaluate/isRandom.py
randomity/evaluate/whyRandom.py
randomity/generate/__init__.py
randomity/generate/pseudo.py
randomity/generate/quantum.py
randomity/generate/algos/__init__.py
randomity/generate/algos/algo_BlumBlumShub.py
randomity/generate/algos/algo_LCG.py
randomity/generate/algos/algo_MTNumpy.py
randomity/generate/algos/algo_MersenneTwister.py
randomity/generate/algos/algo_MiddleSquare.py
randomity/generate/algos/algo_XORShift.py
randomity-0.5.3.dist-info/METADATA
randomity-0.5.3.dist-info/WHEEL
randomity-0.5.3.dist-info/licenses/LICENSE
randomity-0.5.3.dist-info/RECORD
