Metadata-Version: 2.4
Name: randomity
Version: 0.5.3
Summary: A package for generating and assessing randomness.
Project-URL: Repository, https://github.com/SepehrAkbari/randomity
Project-URL: Changelog, https://github.com/SepehrAkbari/randomity/blob/main/releases.md
Author-email: Sepehr Akbari <isepehrakbari@gmail.com>
License-File: LICENSE
Keywords: PRNG,TRNG,predictability,random,randomness
Classifier: Development Status :: 4 - Beta
Classifier: Intended Audience :: Developers
Classifier: Intended Audience :: Education
Classifier: Intended Audience :: Science/Research
Classifier: License :: OSI Approved :: GNU General Public License v3 (GPLv3)
Classifier: Operating System :: OS Independent
Classifier: Programming Language :: Python :: 3
Classifier: Topic :: Scientific/Engineering :: Mathematics
Classifier: Topic :: Software Development :: Libraries :: Python Modules
Classifier: Topic :: Utilities
Requires-Python: >=3.7
